Metadata-Version: 2.1
Name: notebook-restified
Version: 0.1.0
Summary: An implementation of MVC concepts in Jupyter
Home-page: https://github.com/kafonek/notebook_restified
Author: Matt Kafonek
Author-email: kafonek@gmail.com
License: BSD
Platform: UNKNOWN
